lavague/contexts/anthropic/__init__.py
lavague/contexts/anthropic/base.py
lavague_contexts_anthropic-0.1.3.dist-info/METADATA
lavague_contexts_anthropic-0.1.3.dist-info/WHEEL
lavague_contexts_anthropic-0.1.3.dist-info/RECORD
