Metadata-Version: 2.1
Name: lavague-contexts-anthropic
Version: 0.1.3
Summary: anthropic integration for lavague
Home-page: https://lavague.ai
License: Apache-2.0
Keywords: LAM,action,automation,LLM,NLP,RAG,selenium,playwright
Author: lavague-ai
Requires-Python: >=3.10.0,<3.12
Classifier: Development Status :: 3 - Alpha
Classifier: Intended Audience :: Developers
Classifier: License :: OSI Approved :: Apache Software License
Classifier: Programming Language :: Python :: 3
Classifier: Programming Language :: Python :: 3.10
Classifier: Programming Language :: Python :: 3.11
Classifier: Topic :: Scientific/Engineering :: Artificial Intelligence
Classifier: Topic :: Software Development :: Libraries :: Application Frameworks
Classifier: Topic :: Software Development :: Libraries :: Python Modules
Requires-Dist: lavague-core (>=0.2.26,<0.3.0)
Requires-Dist: llama-index-llms-anthropic (==0.1.15)
Requires-Dist: llama-index-multi-modal-llms-anthropic (>=0.1.6,<0.2.0)
Project-URL: Documentation, https://docs.lavague.ai/en/latest/
Project-URL: Repository, https://github.com/lavague-ai/LaVague/
